pypi2cwl/__init__.py
pypi2cwl/pypi2cwl.py
pypi2cwl/test_pypi2cwl.py
pypi2cwl-0.1.0.dist-info/DESCRIPTION.rst
pypi2cwl-0.1.0.dist-info/METADATA
pypi2cwl-0.1.0.dist-info/RECORD
pypi2cwl-0.1.0.dist-info/WHEEL
pypi2cwl-0.1.0.dist-info/entry_points.txt
pypi2cwl-0.1.0.dist-info/metadata.json
pypi2cwl-0.1.0.dist-info/top_level.txt
